{
    "id": 33,
    "name": "CopyFile",
    "description": "Copies a file from a directory to another",
    "category": 1,
    "version": "1.0.0",
    "inputs": [
        {
            "name": "sourceDirectory",
            "type": "string",
            "default_value": "NA",
            "description": "Path of the source folder"
        },
        {
            "name": "sourceFileName",
            "type": "string",
            "default_value": "NA",
            "description": "Name of the file to be copied"
        },
        {
            "name": "targetDirectory",
            "type": "string",
            "default_value": "NA",
            "description": "Path of the target folder"
        },
        {
            "name": "targetFileName",
            "type": "string",
            "default_value": "NA",
            "description": "Name of the file which is to given to copied file"
        },
        {
            "name": "sourceDirectory",
            "type": "string",
            "default_value": "NA",
            "description": "Path of the source folder"
        },
        {
            "name": "sourceFileName",
            "type": "string",
            "default_value": "NA",
            "description": "Name of the file to be copied"
        },
        {
            "name": "targetDirectory",
            "type": "string",
            "default_value": "NA",
            "description": "Path of the target folder"
        },
        {
            "name": "targetFileName",
            "type": "string",
            "default_value": "NA",
            "description": "Name of the file which is to given to copied file"
        }
    ],
    "outputs": [
        {
            "name": "targetFilePath",
            "type": "string",
            "description": "Path of the copied file"
        },
        {
            "name": "status",
            "type": "string",
            "description": "Status of the process execution"
        },
        {
            "name": "targetFilePath",
            "type": "string",
            "description": "Path of the copied file"
        },
        {
            "name": "status",
            "type": "string",
            "description": "Status of the process execution"
        }
    ],
    "dependencies": [],
    "authors": [],
    "errors": [
        {
            "message": "FOLDER_NOT_FOUND",
            "code": "X1000000000",
            "description": "Source folder not found"
        },
        {
            "message": "FOLDER_NOT_FOUND",
            "code": "X1000000002",
            "description": "Target folder not found"
        },
        {
            "message": "FILE_NOT_FOUND",
            "code": "X1000000001",
            "description": "Source File not found"
        },
        {
            "message": "FILE_NOT_FOUND",
            "code": "X1000000003",
            "description": "Target File not found"
        },
        {
            "message": "FOLDER_NOT_FOUND",
            "code": "X1000000000",
            "description": "Source folder not found"
        },
        {
            "message": "FOLDER_NOT_FOUND",
            "code": "X1000000002",
            "description": "Target folder not found"
        },
        {
            "message": "FILE_NOT_FOUND",
            "code": "X1000000001",
            "description": "Source File not found"
        },
        {
            "message": "FILE_NOT_FOUND",
            "code": "X1000000003",
            "description": "Target File not found"
        }
    ],
    "added_by": 1
}